pyconverters_pypowerpoint/__init__.py
pyconverters_pypowerpoint/pypowerpoint.py
pyconverters_pypowerpoint/pptx2md/log.py
pyconverters_pypowerpoint/pptx2md/multi_column.py
pyconverters_pypowerpoint/pptx2md/outputter.py
pyconverters_pypowerpoint/pptx2md/parser.py
pyconverters_pypowerpoint/pptx2md/types.py
pyconverters_pypowerpoint/pptx2md/utils.py
pyconverters_pypowerpoint-0.5.34.dist-info/entry_points.txt
pyconverters_pypowerpoint-0.5.34.dist-info/licenses/LICENSE
pyconverters_pypowerpoint-0.5.34.dist-info/WHEEL
pyconverters_pypowerpoint-0.5.34.dist-info/METADATA
pyconverters_pypowerpoint-0.5.34.dist-info/RECORD
