Metadata-Version: 2.4
Name: pyconverters-pypowerpoint
Version: 0.5.34
Summary: Convert PPTX to text using [python-pptx]
Home-page: https://github.com/oterrier/pyconverters_pypowerpoint/
Keywords: 
Author: Olivier Terrier
Author-email: olivier.terrier@kairntech.com
Requires-Python: >=3.8
Classifier: Intended Audience :: Information Technology
Classifier: Intended Audience :: Developers
Classifier: Intended Audience :: System Administrators
Classifier: Operating System :: OS Independent
Classifier: Topic :: Software Development :: Libraries :: Application Frameworks
Classifier: Topic :: Software Development :: Libraries :: Python Modules
Classifier: Topic :: Software Development :: Libraries
Classifier: Topic :: Software Development
Classifier: License :: OSI Approved :: MIT License
Classifier: Development Status :: 4 - Beta
Classifier: Programming Language :: Python :: 3.8
License-File: LICENSE
Requires-Dist: pymultirole-plugins>=0.5.0,<0.6.0
Requires-Dist: python-pptx
Requires-Dist: rapidfuzz
Requires-Dist: tqdm
Requires-Dist: scipy
Requires-Dist: numpy
Requires-Dist: Pillow>=6.0.0
Requires-Dist: filetype==1.0.13
Requires-Dist: wand==0.6.13
Requires-Dist: flit ; extra == "dev"
Requires-Dist: pre-commit ; extra == "dev"
Requires-Dist: bump2version ; extra == "dev"
Requires-Dist: sphinx ; extra == "docs"
Requires-Dist: sphinx-rtd-theme ; extra == "docs"
Requires-Dist: m2r2 ; extra == "docs"
Requires-Dist: sphinxcontrib.apidoc ; extra == "docs"
Requires-Dist: jupyter_sphinx ; extra == "docs"
Requires-Dist: pytest ; extra == "test"
Requires-Dist: pytest-cov ; extra == "test"
Requires-Dist: pytest-flake8 ; extra == "test"
Requires-Dist: pytest-black ; extra == "test"
Requires-Dist: flake8==3.9.2 ; extra == "test"
Requires-Dist: tox ; extra == "test"
Provides-Extra: dev
Provides-Extra: docs
Provides-Extra: test
